weather.py
weather_wyq-0.1.0.dist-info/METADATA
weather_wyq-0.1.0.dist-info/WHEEL
weather_wyq-0.1.0.dist-info/top_level.txt
weather_wyq-0.1.0.dist-info/RECORD
